pricegrabber/__init__.py
pricegrabber/exceptions.py
pricegrabber/grabber.py
pricegrabber/siteconfig.py
pricegrabber/testrunner.py
pricegrabber/util.py
pricegrabber-0.0.1.dist-info/METADATA
pricegrabber-0.0.1.dist-info/WHEEL
pricegrabber-0.0.1.dist-info/top_level.txt
pricegrabber-0.0.1.dist-info/RECORD
