Metadata-Version: 2.1
Name: pricegrabber
Version: 0.0.1
Summary: Package to scrape prices from various websites
Home-page: https://github.com/tinloaf/pricegrabber
Author: Lukas Barth
Author-email: mail@tinloaf.de
License: MIT
Keywords: library prices scraping
Platform: UNKNOWN
Classifier: Programming Language :: Python :: 3
Classifier: License :: OSI Approved :: MIT License
Classifier: Operating System :: OS Independent
Classifier: Development Status :: 3 - Alpha
Classifier: Intended Audience :: Developers
Classifier: Topic :: Internet :: WWW/HTTP
Classifier: Topic :: Software Development :: Libraries
Requires-Dist: requests (>=2.21.0)
Requires-Dist: lxml (>=4.2.5)
